api/api.py
api/config.py
api/run.py
api/static/config1.png
api/static/config2.png
api/static/script.js
api/templates/index.html
yourtube/__init__.py
yourtube/async_worker.py
yourtube/config.json.template
yourtube/database.py
yourtube/main.py
yourtube/monitor.py
yourtube/prompts.py
yourtube/reporter.py
yourtube/scanner.py
yourtube/transcriber.py
yourtube/utils.py
video_curator-1.2.1.dist-info/METADATA
video_curator-1.2.1.dist-info/WHEEL
video_curator-1.2.1.dist-info/entry_points.txt
video_curator-1.2.1.dist-info/top_level.txt
video_curator-1.2.1.dist-info/RECORD
