Metadata-Version: 2.2
Name: video-curator
Version: 1.2.1
Summary: Your own youtube assistant
Requires-Python: >=3.10
Requires-Dist: google-api-python-client>=2.158.0
Requires-Dist: openai-whisper>=20240930
Requires-Dist: torch>=2.5.1
Requires-Dist: yt-dlp>=2024.12.23
Requires-Dist: openai>=1.0.0
Requires-Dist: pytest>=8.3.4
Requires-Dist: litellm>=1.58.2
Requires-Dist: webvtt-py>=0.5.1
Requires-Dist: sqlalchemy>=2.0.37
Requires-Dist: markdown>=3.7
Requires-Dist: ffmpeg-python>=0.2.0
Requires-Dist: fastapi>=0.115.8
Requires-Dist: uvicorn>=0.34.0
Requires-Dist: schedule>=1.2.2
Requires-Dist: aiosmtplib>=4.0.0
Requires-Dist: flask>=3.1.0
Requires-Dist: flask-cors>=5.0.1
